{
  "$comment": "Credential Event extension conformance fixtures (v0.11.3+, DD-145)",
  "version": "0.11.3",
  "valid": [
    {
      "name": "issued-credential",
      "input": {
        "event": "issued",
        "credential_ref": "sha256:e3b0c44298fc1c149afbf4c8996fb92427ae41e4649b934ca495991b7852b855",
        "authority": "https://issuer.example.com"
      }
    },
    {
      "name": "rotated-with-previous",
      "input": {
        "event": "rotated",
        "credential_ref": "sha256:a1b2c3d4e5f6a7b8c9d0e1f2a3b4c5d6e7f8a9b0c1d2e3f4a5b6c7d8e9f0a1b2",
        "authority": "https://ca.example.com",
        "previous_ref": "sha256:e3b0c44298fc1c149afbf4c8996fb92427ae41e4649b934ca495991b7852b855"
      }
    },
    {
      "name": "revoked-with-expiry",
      "input": {
        "event": "revoked",
        "credential_ref": "hmac-sha256:f0e1d2c3b4a5968778695a4b3c2d1e0ff0e1d2c3b4a5968778695a4b3c2d1e0f",
        "authority": "https://security.example.com",
        "expires_at": "2026-12-31T23:59:59Z"
      }
    }
  ],
  "invalid": [
    {
      "name": "invalid-event-type",
      "input": {
        "event": "deleted",
        "credential_ref": "sha256:e3b0c44298fc1c149afbf4c8996fb92427ae41e4649b934ca495991b7852b855",
        "authority": "https://issuer.example.com"
      }
    },
    {
      "name": "non-https-authority",
      "input": {
        "event": "issued",
        "credential_ref": "sha256:e3b0c44298fc1c149afbf4c8996fb92427ae41e4649b934ca495991b7852b855",
        "authority": "http://issuer.example.com"
      }
    },
    {
      "name": "invalid-credential-ref-format",
      "input": {
        "event": "issued",
        "credential_ref": "md5:abc123",
        "authority": "https://issuer.example.com"
      }
    }
  ]
}
